neurolib/__init__.py
neurolib/data/datasets/gw/subjects/NAP_001/functional/BOLD_rsfMRI.mat
neurolib/data/datasets/gw/subjects/NAP_001/structural/DTI_CM.mat
neurolib/data/datasets/gw/subjects/NAP_001/structural/DTI_LEN.mat
neurolib/data/datasets/gw/subjects/NAP_002/functional/BOLD_rsfMRI.mat
neurolib/data/datasets/gw/subjects/NAP_002/structural/DTI_CM.mat
neurolib/data/datasets/gw/subjects/NAP_002/structural/DTI_LEN.mat
neurolib/data/datasets/gw/subjects/NAP_007/functional/BOLD_rsfMRI.mat
neurolib/data/datasets/gw/subjects/NAP_007/structural/DTI_CM.mat
neurolib/data/datasets/gw/subjects/NAP_007/structural/DTI_LEN.mat
neurolib/data/datasets/gw/subjects/NAP_009/functional/BOLD_rsfMRI.mat
neurolib/data/datasets/gw/subjects/NAP_009/structural/DTI_CM.mat
neurolib/data/datasets/gw/subjects/NAP_009/structural/DTI_LEN.mat
neurolib/data/datasets/gw/subjects/NAP_013/functional/BOLD_rsfMRI.mat
neurolib/data/datasets/gw/subjects/NAP_013/structural/DTI_CM.mat
neurolib/data/datasets/gw/subjects/NAP_013/structural/DTI_LEN.mat
neurolib/data/datasets/hcp/subjects/101309/functional/TC_rsfMRI_REST1_LR.mat
neurolib/data/datasets/hcp/subjects/101309/structural/DTI_CM.mat
neurolib/data/datasets/hcp/subjects/101309/structural/DTI_LEN.mat
neurolib/data/datasets/hcp/subjects/101309/structural/nvoxel.txt
neurolib/data/datasets/hcp/subjects/101309/structural/waytotal.txt
neurolib/data/datasets/hcp/subjects/102311/functional/TC_rsfMRI_REST1_LR.mat
neurolib/data/datasets/hcp/subjects/102311/structural/DTI_CM.mat
neurolib/data/datasets/hcp/subjects/102311/structural/DTI_LEN.mat
neurolib/data/datasets/hcp/subjects/102311/structural/nvoxel.txt
neurolib/data/datasets/hcp/subjects/102311/structural/waytotal.txt
neurolib/data/datasets/hcp/subjects/102816/functional/TC_rsfMRI_REST1_LR.mat
neurolib/data/datasets/hcp/subjects/102816/structural/DTI_CM.mat
neurolib/data/datasets/hcp/subjects/102816/structural/DTI_LEN.mat
neurolib/data/datasets/hcp/subjects/102816/structural/nvoxel.txt
neurolib-0.6.2.dist-info/LICENSE
neurolib-0.6.2.dist-info/METADATA
neurolib-0.6.2.dist-info/WHEEL
neurolib-0.6.2.dist-info/top_level.txt
neurolib-0.6.2.dist-info/RECORD
