Metadata-Version: 2.1
Name: neurolib
Version: 0.6.2
Summary: Easy whole-brain neural mass modeling
Home-page: https://github.com/neurolib-dev/neurolib
Author: Caglar Cakan
Author-email: cakan@ni.tu-berlin.de
License: MIT
Platform: UNKNOWN
Classifier: Programming Language :: Python :: 3
Classifier: License :: OSI Approved :: MIT License
Classifier: Operating System :: OS Independent
Requires-Python: >=3.6
License-File: LICENSE
Requires-Dist: psutil
Requires-Dist: h5py
Requires-Dist: numba
Requires-Dist: numpy
Requires-Dist: scipy
Requires-Dist: xarray
Requires-Dist: pandas
Requires-Dist: tqdm
Requires-Dist: pypet
Requires-Dist: deap
Requires-Dist: dill
Requires-Dist: sympy
Requires-Dist: jitcdde
Requires-Dist: dpath
